MANIFEST.in
README.md
pyproject.toml
setup.cfg
setup.py
kafkahood/__init__.py
kafkahood/kafkahood.py
kafkahood.egg-info/PKG-INFO
kafkahood.egg-info/SOURCES.txt
kafkahood.egg-info/dependency_links.txt
kafkahood.egg-info/requires.txt
kafkahood.egg-info/top_level.txt