Metadata-Version: 2.1
Name: kafkahood
Version: 0.1.1
Summary: An internal Python package for Kafka configuration and streaming of topics
Home-page: https://github.com/fbasurto/kafkahood
Author: Michael Miller
Author-email: michaelomiller98@gmail.com
Classifier: Programming Language :: Python :: 3
Classifier: License :: OSI Approved :: MIT License
Classifier: Operating System :: OS Independent
Requires-Python: >=3.6
Requires-Dist: pyyaml
